[{"FK_TipoCurso":2,"FK_IDCurso":2,"nameInstructor":"Jose Antonio Cruz Romero","FK_Instructor":5,"FK_Becario":213,"nameBecario":"MANUEL LORETO AGUILERA RUIZ","apto":1,"fecha":"04-09-2023","observaciones":"Observaciones del curso tiene detalles al manejor","Puntos":10,"Valores":14,"califf":9},{"FK_TipoCurso":2,"FK_IDCurso":2,"nameInstructor":"Jose Antonio Cruz Romero","FK_Instructor":5,"FK_Becario":213,"nameBecario":"MANUEL LORETO AGUILERA RUIZ","apto":1,"fecha":"04-09-2023","observaciones":"nuevos comentarios","Puntos":8,"Valores":10,"califf":8}]